{"cameraMode":{"drawMode":0,"name":"Shaded","section":"Shading Mode"},"sceneLighting":true,"audioPlay":false,"sceneViewState":{"m_AlwaysRefresh":false,"showFog":true,"showSkybox":false,"showFlares":true,"showImageEffects":true,"showParticleSystems":true,"showVisualEffectGraphs":true,"m_FxEnabled":true},"in2DMode":false,"pivot":{"x":13.98787784576416,"y":4.819585800170898,"z":38.08109664916992},"rotation":{"x":0.14760130643844605,"y":0.09331410378217697,"z":-0.013985439203679562,"w":0.9845457077026367},"size":3.56343150138855,"orthographic":false}